pyhtmlgui/__init__.py
pyhtmlgui/pyhtmlgui.py
pyhtmlgui/pyhtmlguiInstance.py
pyhtmlgui/apps/__init__.py
pyhtmlgui/apps/pyHtmlChromeApp.py
pyhtmlgui/apps/qt/__init__.py
pyhtmlgui/apps/qt/pyHtmlQtApp.py
pyhtmlgui/assets/electron/main.js
pyhtmlgui/assets/electron/package.json
pyhtmlgui/assets/electron/pyhtmlgui.js
pyhtmlgui/lib/__init__.py
pyhtmlgui/lib/browser.py
pyhtmlgui/lib/observable.py
pyhtmlgui/lib/observableDict.py
pyhtmlgui/lib/observableList.py
pyhtmlgui/lib/weakFunctionReferences.py
pyhtmlgui/templates/pyHtmlGuiBase.html
pyhtmlgui/view/__init__.py
pyhtmlgui/view/observableDictView.py
pyhtmlgui/view/observableListView.py
pyhtmlgui/view/pyhtmlview.py
pyhtmlgui-3.22.dist-info/LICENSE
pyhtmlgui-3.22.dist-info/METADATA
pyhtmlgui-3.22.dist-info/WHEEL
pyhtmlgui-3.22.dist-info/top_level.txt
pyhtmlgui-3.22.dist-info/RECORD
