Metadata-Version: 2.1
Name: pyhtmlgui
Version: 3.22
Summary: A Python library for building user interfaces
Home-page: https://github.com/dirk-makerhafen/pyHtmlGui
Author: Dirk Makerhafen
Author-email: dirk@makerhafen.de
License: MIT
Classifier: Programming Language :: Python :: 3
Classifier: License :: OSI Approved :: MIT License
Classifier: Operating System :: OS Independent
Requires-Python: >=3.7
License-File: LICENSE
